{"name":"introduction","slug":"introduction","count":1,"postlist":[{"title":"博客说明","uid":"7b743f848a5ccca097f084681149d4d7","slug":"博客说明","date":"2021-12-01T10:49:36.000Z","updated":"2021-12-01T13:44:40.331Z","comments":true,"path":"api/articles/博客说明.json","keywords":null,"cover":"https://z3.ax1x.com/2021/12/01/oJml4K.png","text":"The Introduction to my BlogToday is the December first and I recreate my blog, since today I am going to upload something what I’ve done or ...","link":"","photos":[],"count_time":{"symbolsCount":166,"symbolsTime":"1 mins."},"categories":[{"name":"introduction","slug":"introduction","count":1,"path":"api/categories/introduction.json"}],"tags":[{"name":"博客","slug":"博客","count":1,"path":"api/tags/博客.json"}],"author":{"name":"JerryYan","slug":"blog-author","avatar":"https://z3.ax1x.com/2021/12/01/oJTH4U.png","link":"/","description":"A student from CQU","socials":{"github":"","twitter":"","stackoverflow":"","wechat":"","qq":"","weibo":"","zhihu":"","csdn":"","juejin":"","customs":{}}},"feature":true,"pinned":true}]}